{
    "runden_timestamp": "2026-04-06_19-00-33",
    "tournament": "Ak-Schafkopf-4",
    "User": "Stefan K.",
    "start_info": "",
    "ende_info": true,
    "spieler": [
        "Stefan K.",
        "Elias S.",
        "Lukas H.",
        "Davina"
    ],
    "spiele": [
        {
            "Zeitstempel": "2026-04-06_19-01-01",
            "Spielart": "Geier",
            "Spielmacher": "Davina",
            "Rufpartner": null,
            "Klopfer": 1,
            "Gewonnen": true,
            "Wert": 12,
            "Wert_NK": 6,
            "Wert_Wue": 8,
            "Wert_Wue_NK": 4,
            "Verteilungsfaktor": 1,
            "Mitspieler_Runde": [
                "Stefan K.",
                "Elias S.",
                "Lukas H.",
                "Davina"
            ],
            "spiel_info": {
                "Spielart": "Geier",
                "Klopfer": 1,
                "Laufende": 0,
                "Tout": false,
                "Sie": false,
                "Jungfrau": 0,
                "Schneider": true,
                "Schwarz": false,
                "Kontra": false,
                "Gewonnen": true
            }
        },
        {
            "Zeitstempel": "2026-04-06_19-06-38",
            "Spielart": "Ruf",
            "Spielmacher": "Elias S.",
            "Rufpartner": "Davina",
            "Klopfer": 1,
            "Gewonnen": true,
            "Wert": 2,
            "Wert_NK": 1,
            "Wert_Wue": 2,
            "Wert_Wue_NK": 1,
            "Verteilungsfaktor": 0.5,
            "Mitspieler_Runde": [
                "Stefan K.",
                "Elias S.",
                "Lukas H.",
                "Davina"
            ],
            "spiel_info": {
                "Spielart": "Ruf",
                "Klopfer": 1,
                "Laufende": 0,
                "Tout": false,
                "Sie": false,
                "Jungfrau": 0,
                "Schneider": false,
                "Schwarz": false,
                "Kontra": false,
                "Gewonnen": true
            }
        },
        {
            "Zeitstempel": "2026-04-06_19-11-16",
            "Spielart": "Ramsch",
            "Spielmacher": "Davina",
            "Rufpartner": null,
            "Klopfer": 1,
            "Gewonnen": false,
            "Wert": 2,
            "Wert_NK": 1,
            "Wert_Wue": 2,
            "Wert_Wue_NK": 1,
            "Verteilungsfaktor": 1,
            "Mitspieler_Runde": [
                "Stefan K.",
                "Elias S.",
                "Lukas H.",
                "Davina"
            ],
            "spiel_info": {
                "Spielart": "Ramsch",
                "Klopfer": 1,
                "Laufende": 0,
                "Tout": false,
                "Sie": false,
                "Jungfrau": 0,
                "Schneider": false,
                "Schwarz": false,
                "Kontra": false,
                "Gewonnen": false
            }
        },
        {
            "Zeitstempel": "2026-04-06_19-17-39",
            "Spielart": "Ruf",
            "Spielmacher": "Stefan K.",
            "Rufpartner": "Davina",
            "Klopfer": 1,
            "Gewonnen": true,
            "Wert": 2,
            "Wert_NK": 1,
            "Wert_Wue": 2,
            "Wert_Wue_NK": 1,
            "Verteilungsfaktor": 0.5,
            "Mitspieler_Runde": [
                "Stefan K.",
                "Elias S.",
                "Lukas H.",
                "Davina"
            ],
            "spiel_info": {
                "Spielart": "Ruf",
                "Klopfer": 1,
                "Laufende": 0,
                "Tout": false,
                "Sie": false,
                "Jungfrau": 0,
                "Schneider": false,
                "Schwarz": false,
                "Kontra": false,
                "Gewonnen": true
            }
        }
    ]
}