{
    "runden_timestamp": "2026-02-11_15-35-30",
    "tournament": "Ak-Schafkopf-3",
    "User": "Gaudi Sepp",
    "start_info": "",
    "spieler": [
        "Elias S.",
        "Lukas H.",
        "Tim Plote",
        "Stefan K.",
        "Kira"
    ],
    "spiele": [
        {
            "Zeitstempel": "2026-02-11_15-39-13",
            "Spielart": "Ramsch",
            "Spielmacher": "Stefan K.",
            "Rufpartner": null,
            "Klopfer": 0,
            "Gewonnen": false,
            "Wert": 1,
            "Wert_NK": 1,
            "Wert_Wue": 1,
            "Wert_Wue_NK": 1,
            "Verteilungsfaktor": 1,
            "Mitspieler_Runde": [
                "Elias S.",
                "Lukas H.",
                "Tim Plote",
                "Stefan K."
            ]
        },
        {
            "Zeitstempel": "2026-02-11_15-44-51",
            "Spielart": "Ruf",
            "Spielmacher": "Tim Plote",
            "Rufpartner": "Lukas H.",
            "Klopfer": 0,
            "Gewonnen": false,
            "Wert": 1,
            "Wert_NK": 1,
            "Wert_Wue": 2,
            "Wert_Wue_NK": 2,
            "Verteilungsfaktor": 0.5,
            "Mitspieler_Runde": [
                "Elias S.",
                "Lukas H.",
                "Tim Plote",
                "Kira"
            ]
        },
        {
            "Zeitstempel": "2026-02-11_15-49-04",
            "Spielart": "Ruf",
            "Spielmacher": "Kira",
            "Rufpartner": "Tim Plote",
            "Klopfer": 1,
            "Gewonnen": false,
            "Wert": 2,
            "Wert_NK": 1,
            "Wert_Wue": 4,
            "Wert_Wue_NK": 2,
            "Verteilungsfaktor": 0.5,
            "Mitspieler_Runde": [
                "Lukas H.",
                "Tim Plote",
                "Stefan K.",
                "Kira"
            ]
        },
        {
            "Zeitstempel": "2026-02-11_15-54-38",
            "Spielart": "Ruf",
            "Spielmacher": "Lukas H.",
            "Rufpartner": "Tim Plote",
            "Klopfer": 1,
            "Gewonnen": true,
            "Wert": 4,
            "Wert_NK": 2,
            "Wert_Wue": 4,
            "Wert_Wue_NK": 2,
            "Verteilungsfaktor": 0.5,
            "Mitspieler_Runde": [
                "Elias S.",
                "Lukas H.",
                "Tim Plote",
                "Stefan K."
            ]
        },
        {
            "Zeitstempel": "2026-02-11_16-00-52",
            "Spielart": "Wenz",
            "Spielmacher": "Elias S.",
            "Rufpartner": null,
            "Klopfer": 1,
            "Gewonnen": true,
            "Wert": 10,
            "Wert_NK": 5,
            "Wert_Wue": 6,
            "Wert_Wue_NK": 3,
            "Verteilungsfaktor": 1,
            "Mitspieler_Runde": [
                "Elias S.",
                "Tim Plote",
                "Stefan K.",
                "Kira"
            ]
        },
        {
            "Zeitstempel": "2026-02-11_16-04-49",
            "Spielart": "Ruf",
            "Spielmacher": "Kira",
            "Rufpartner": "Elias S.",
            "Klopfer": 2,
            "Gewonnen": true,
            "Wert": 16,
            "Wert_NK": 4,
            "Wert_Wue": 6,
            "Wert_Wue_NK": 4,
            "Verteilungsfaktor": 0.5,
            "Mitspieler_Runde": [
                "Elias S.",
                "Lukas H.",
                "Tim Plote",
                "Kira"
            ]
        },
        {
            "Zeitstempel": "2026-02-11_16-11-35",
            "Spielart": "Wenz",
            "Spielmacher": "Lukas H.",
            "Rufpartner": null,
            "Klopfer": 0,
            "Gewonnen": false,
            "Wert": 5,
            "Wert_NK": 5,
            "Wert_Wue": 3,
            "Wert_Wue_NK": 3,
            "Verteilungsfaktor": 1,
            "Mitspieler_Runde": [
                "Elias S.",
                "Lukas H.",
                "Tim Plote",
                "Kira"
            ]
        },
        {
            "Zeitstempel": "2026-02-11_16-16-54",
            "Spielart": "Wenz",
            "Spielmacher": "Lukas H.",
            "Rufpartner": null,
            "Klopfer": 1,
            "Gewonnen": false,
            "Wert": 14,
            "Wert_NK": 7,
            "Wert_Wue": 8,
            "Wert_Wue_NK": 5,
            "Verteilungsfaktor": 1,
            "Mitspieler_Runde": [
                "Elias S.",
                "Lukas H.",
                "Tim Plote",
                "Kira"
            ]
        }
    ]
}